airflow_poetry_test/__init__.py
airflow_poetry_test-0.1.2.dist-info/WHEEL
airflow_poetry_test-0.1.2.dist-info/METADATA
airflow_poetry_test-0.1.2.dist-info/RECORD
